Cardspck/Baraja.py
Cardspck/Carta.py
Cardspck/__init__.py
AhmerCards-0.0.1.dist-info/METADATA
AhmerCards-0.0.1.dist-info/WHEEL
AhmerCards-0.0.1.dist-info/top_level.txt
AhmerCards-0.0.1.dist-info/RECORD
