Metadata-Version: 2.1
Name: AhmerCards
Version: 0.0.1
Summary: programa para jugar alas cartas
Home-page: UNKNOWN
Author: Ahmer Muhammad
Author-email: ahmerishere@gmail.com
License: MIT
Platform: UNKNOWN
Classifier: Programming Language :: Python :: 3
Classifier: License :: OSI Approved :: MIT License
Classifier: Operating System :: OS Independent
Requires-Dist: pickle
